fraud_detection_model/VERSION
fraud_detection_model/__init__.py
fraud_detection_model/config.yml
fraud_detection_model/pipeline.py
fraud_detection_model/predict.py
fraud_detection_model/train_pipeline.py
fraud_detection_model/config/__init__.py
fraud_detection_model/config/core.py
fraud_detection_model/data/__init__.py
fraud_detection_model/data/interim/__init__.py
fraud_detection_model/data/interim/test.csv
fraud_detection_model/data/interim/train.csv
fraud_detection_model/data/raw/__init__.py
fraud_detection_model/models/__init__.py
fraud_detection_model/models/fraud_detection_model_output_v2.0.0.pkl
fraud_detection_model/processing/__init__.py
fraud_detection_model/processing/data_manager.py
fraud_detection_model/processing/features.py
fraud_detection_model/processing/validation.py
fraud_detection_model-2.0.0.dist-info/LICENSE
fraud_detection_model-2.0.0.dist-info/METADATA
fraud_detection_model-2.0.0.dist-info/WHEEL
fraud_detection_model-2.0.0.dist-info/top_level.txt
fraud_detection_model-2.0.0.dist-info/RECORD
